ctxinject/__init__.py
ctxinject/inject.py
ctxinject/model.py
ctxinject/overrides.py
ctxinject/py.typed
ctxinject/resolvers.py
ctxinject/runner.py
ctxinject/sigcheck.py
ctxinject/validation.py
ctxinject-0.1.13.dist-info/licenses/LICENSE
ctxinject-0.1.13.dist-info/METADATA
ctxinject-0.1.13.dist-info/WHEEL
ctxinject-0.1.13.dist-info/top_level.txt
ctxinject-0.1.13.dist-info/RECORD
