Metadata-Version: 2.4
Name: ctxinject
Version: 0.1.13
Summary: Context-based dependency injection for Python
Author-email: rodbell <bellirodrigo2@gmail.com>
Keywords: DI,context,async
Classifier: Development Status :: 4 - Beta
Classifier: Intended Audience :: Developers
Classifier: License :: OSI Approved :: MIT License
Classifier: Programming Language :: Python
Classifier: Programming Language :: Python :: 3.8
Classifier: Programming Language :: Python :: 3.9
Classifier: Programming Language :: Python :: 3.10
Classifier: Programming Language :: Python :: 3.11
Classifier: Programming Language :: Python :: 3.12
Classifier: Programming Language :: Python :: Implementation :: CPython
Classifier: Topic :: Software Development :: Libraries :: Python Modules
Classifier: Topic :: Utilities
Requires-Python: >=3.8
License-File: LICENSE
Requires-Dist: typemapping>=0.1.7
Requires-Dist: typing-extensions>=4.0.0
Requires-Dist: orjson>=3.8.0
Requires-Dist: python-dateutil>=2.8.0
Requires-Dist: anyio>=3.0.0
Provides-Extra: dev
Requires-Dist: pytest>=7.0.0; extra == "dev"
Requires-Dist: pytest-asyncio>=0.21.0; extra == "dev"
Requires-Dist: pytest-cov>=4.0.0; extra == "dev"
Requires-Dist: mypy>=1.0.0; extra == "dev"
Requires-Dist: black>=22.0.0; extra == "dev"
Requires-Dist: isort>=5.0.0; extra == "dev"
Requires-Dist: flake8>=5.0.0; extra == "dev"
Requires-Dist: ruff>=0.11.10; extra == "dev"
Requires-Dist: twine; extra == "dev"
Requires-Dist: build; extra == "dev"
Requires-Dist: pydantic>=2.0.0; extra == "dev"
Requires-Dist: pydantic[email]>=2.0.0; extra == "dev"
Requires-Dist: requests; extra == "dev"
Provides-Extra: pydantic
Requires-Dist: pydantic>=2.0.0; extra == "pydantic"
Requires-Dist: pydantic[email]>=2.0.0; extra == "pydantic"
Provides-Extra: full
Requires-Dist: ctxinject[dev,pydantic]; extra == "full"
Dynamic: license-file
